{
  "report_id": "cbc_0178",
  "source": "synthetic",
  "report_type": "CBC",
  "category": "Hematology",
  "text_clean": "Prime Diagnostics\n\nREPORT: CBC\nINVESTIGATION          RESULT      UNIT      REFERENCE\nHGB                    16.61      g/dL       12.0-17.0\nWhite Blood Cells      7164.97    /cmm       4000-11000\nRed Blood Cells        39.54                 0-0\nPlatelet Count         1437725.73 /cmm       150000-450000\nHematocrit             123.04                0-0\nMCV                    18.18                 0-0\nMCH                    6.28                  0-0\nMCHC                   4.53                  0-0\nRDW                    27.71                 0-0\nNeutrophils            46.38                 0-0\nLymphocytes            43.53                 0-0",
  "text_noisy": "Prime Diagnostics\n\nREPORT: CBC\nINVESTIGATION          RESULT      UNIT      REFERENCE\nHGB                    16.61      g/dL       12.0-I7.0\nWhite Bl0od Cells      7164.97    /cmm       4O00-11OO0\nRed Blood CelIs        39.54                 0-0\nPlatelet C0unt         1437725.73 /cmm       15O00O-4500O0\nHematocrit             I23 04                0-O\nMCV                    18 18                 O-0\nMCH                    6.28                  0-O\nMCHC                   4 53                  O-0\nRDW                    27 7I                 O-0\nNeutr0phiIs            46.38                 O-0\nLymph0cytes            43 53                 O-0",
  "tests": [
    {
      "test_name": "Hemoglobin",
      "value": 16.61,
      "unit": "g/dL",
      "range_low": 12.0,
      "range_high": 17.0,
      "status": "Normal",
      "span_text": "HGB                    16.61      g/dL       12.0-17.0"
    },
    {
      "test_name": "White Blood Cells",
      "value": 7164.97,
      "unit": "/cmm",
      "range_low": 4000,
      "range_high": 11000,
      "status": "Normal",
      "span_text": "White Blood Cells      7164.97    /cmm       4000-11000"
    },
    {
      "test_name": "Red Blood Cells",
      "value": 39.54,
      "unit": "",
      "range_low": 0,
      "range_high": 0,
      "status": "High",
      "span_text": "Red Blood Cells        39.54                 0-0"
    },
    {
      "test_name": "Platelets",
      "value": 1437725.73,
      "unit": "/cmm",
      "range_low": 150000,
      "range_high": 450000,
      "status": "High",
      "span_text": "Platelet Count         1437725.73 /cmm       150000-450000"
    },
    {
      "test_name": "Hematocrit",
      "value": 123.04,
      "unit": "",
      "range_low": 0,
      "range_high": 0,
      "status": "High",
      "span_text": "Hematocrit             123.04                0-0"
    },
    {
      "test_name": "MCV",
      "value": 18.18,
      "unit": "",
      "range_low": 0,
      "range_high": 0,
      "status": "High",
      "span_text": "MCV                    18.18                 0-0"
    },
    {
      "test_name": "MCH",
      "value": 6.28,
      "unit": "",
      "range_low": 0,
      "range_high": 0,
      "status": "High",
      "span_text": "MCH                    6.28                  0-0"
    },
    {
      "test_name": "MCHC",
      "value": 4.53,
      "unit": "",
      "range_low": 0,
      "range_high": 0,
      "status": "High",
      "span_text": "MCHC                   4.53                  0-0"
    },
    {
      "test_name": "RDW",
      "value": 27.71,
      "unit": "",
      "range_low": 0,
      "range_high": 0,
      "status": "High",
      "span_text": "RDW                    27.71                 0-0"
    },
    {
      "test_name": "Neutrophils",
      "value": 46.38,
      "unit": "",
      "range_low": 0,
      "range_high": 0,
      "status": "High",
      "span_text": "Neutrophils            46.38                 0-0"
    },
    {
      "test_name": "Lymphocytes",
      "value": 43.53,
      "unit": "",
      "range_low": 0,
      "range_high": 0,
      "status": "High",
      "span_text": "Lymphocytes            43.53                 0-0"
    }
  ]
}